rssh/__init__.py
rssh/client.py
rssh/rsa.py
rssh/server.py
rssh-1.1.dist-info/LICENSE
rssh-1.1.dist-info/METADATA
rssh-1.1.dist-info/WHEEL
rssh-1.1.dist-info/top_level.txt
rssh-1.1.dist-info/RECORD
