Metadata-Version: 2.1
Name: rssh
Version: 1.1
Summary: A SSH(Secure Shell) server/client library
Home-page: https://github.com/ReddyyZ/rssh
Author: Arthur Oliveira
Author-email: fantasmahacking7@gmail.com
License: MIT
Platform: UNKNOWN
Classifier: Programming Language :: Python :: 3
Classifier: License :: OSI Approved :: MIT License
Classifier: Operating System :: OS Independent
Requires-Python: >=3.6
Requires-Dist: pycryptodome (>=3.9.4)
